[
    {
        "id": 1,
        "name": "Aloe Vera",
        "image_url": "../assets/aloevera.jpg",
        "description": "A succulent plant species known for its medicinal properties.",
        "price": 100
    },
    {
        "id": 2,
        "name": "Spider Plant",
        "image_url": "../assets/spider_plant.jpg",
        "description": "A resilient plant with arching leaves and small plantlets.",
        "price": 120
    },
    {
        "id": 3,
        "name": "Snake Plant",
        "image_url": "../assets/snake_plant.jpg",
        "description": "A hardy plant with upright, sword-like leaves.",
        "price": 150
    },
    {
        "id": 4,
        "name": "Pothos",
        "image_url": "../assets/pothos.jpg",
        "description": "A low-maintenance vine with heart-shaped leaves.",
        "price": 80
    },
    {
        "id": 5,
        "name": "ZZ Plant",
        "image_url": "../assets/zz_plant.jpg",
        "description": "A tough plant with glossy, dark green leaves.",
        "price": 180
    },
    {
        "id": 6,
        "name": "Peace Lily",
        "image_url": "../assets/peace_lily.jpg",
        "description": "A plant with white blooms and glossy leaves.",
        "price": 200
    },
    {
        "id": 7,
        "name": "English Ivy",
        "image_url": "../assets/english_ivy.jpg",
        "description": "A versatile vine with small, lobed leaves.",
        "price": 140
    },
    {
        "id": 8,
        "name": "Chinese Evergreen",
        "image_url": "../assets/chinese_evergreen.jpg",
        "description": "A plant with attractive, variegated leaves.",
        "price": 160
    },
    {
        "id": 9,
        "name": "Philodendron",
        "image_url": "../assets/philodendron.jpg",
        "description": "A tropical plant with large, glossy leaves.",
        "price": 220
    },
    {
        "id": 10,
        "name": "Fern",
        "image_url": "../assets/fern.jpg",
        "description": "A plant with feathery, green foliage.",
        "price": 120
    },
    {
        "id": 11,
        "name": "Cactus",
        "image_url": "../assets/cactus.jpg",
        "description": "A spiny succulent plant that thrives in dry conditions.",
        "price": 90
    },
    {
        "id": 12,
        "name": "Rubber Plant",
        "image_url": "../assets/rubber_plant.jpg",
        "description": "A large plant with shiny, dark green leaves.",
        "price": 250
    },
    {
        "id": 13,
        "name": "Dracaena",
        "image_url": "../assets/dracaena.jpg",
        "description": "A plant with long, arching leaves and a woody stem.",
        "price": 170
    },
    {
        "id": 14,
        "name": "Bamboo Palm",
        "image_url": "../assets/bamboo_palm.jpg",
        "description": "A palm with thin, bamboo-like stems and feathery leaves.",
        "price": 300
    },
    {
        "id": 15,
        "name": "Begonia",
        "image_url": "../assets/begonia.jpg",
        "description": "A plant with vibrant, patterned leaves and colorful flowers.",
        "price": 130
    },
    {
        "id": 16,
        "name": "Pilea",
        "image_url": "../assets/pilea.jpg",
        "description": "A plant with unique, round leaves and a compact growth habit.",
        "price": 110
    },
    {
        "id": 17,
        "name": "Kalanchoe",
        "image_url": "../assets/kalanchoe.jpg",
        "description": "A succulent plant with colorful, tubular flowers.",
        "price": 140
    },
    {
        "id": 18,
        "name": "Echeveria",
        "image_url": "../assets/echeveria.jpg",
        "description": "A rosette-shaped succulent with thick, fleshy leaves.",
        "price": 150
    },
    {
        "id": 19,
        "name": "Aloe",
        "image_url": "../assets/aloe.jpg",
        "description": "A plant with spiky leaves and medicinal gel.",
        "price": 100
    },
    {
        "id": 20,
        "name": "Jade Plant",
        "image_url": "../assets/jade_plant.jpg",
        "description": "A succulent with round, fleshy leaves and a tree-like appearance.",
        "price": 120
    },
    {
        "id": 21,
        "name": "African Violet",
        "image_url": "../assets/african_violet.jpg",
        "description": "A plant with fuzzy leaves and vibrant purple flowers.",
        "price": 180
    },
    {
        "id": 22,
        "name": "Hoya",
        "image_url": "../assets/hoya.jpg",
        "description": "A plant with waxy leaves and star-shaped flowers.",
        "price": 200
    },
    {
        "id": 23,
        "name": "Orchid",
        "image_url": "../assets/orchid.jpg",
        "description": "A tropical plant with exotic, showy flowers.",
        "price": 250
    },
    {
        "id": 24,
        "name": "Fiddle Leaf Fig",
        "image_url": "../assets/fiddle_leaf_fig.jpg",
        "description": "A large plant with glossy, violin-shaped leaves.",
        "price": 300
    },
    {
        "id": 25,
        "name": "Ponytail Palm",
        "image_url": "../assets/ponytail_palm.jpg",
        "description": "A plant with a bulbous trunk and long, thin leaves.",
        "price": 220
    },
    {
        "id": 26,
        "name": "Geranium",
        "image_url": "../assets/geranium.jpg",
        "description": "A plant with round leaves and clusters of colorful flowers.",
        "price": 140
    },
    {
        "id": 27,
        "name": "Hibiscus",
        "image_url": "../assets/hibiscus.jpg",
        "description": "A plant with large, trumpet-shaped flowers.",
        "price": 160
    },
    {
        "id": 28,
        "name": "Lemon Balm",
        "image_url": "../assets/lemon_blam.jpg",
        "description": "A fragrant herb with lemon-scented leaves.",
        "price": 100
    },
    {
        "id": 29,
        "name": "Mint",
        "image_url": "../assets/mint.jpg",
        "description": "A hardy herb with aromatic, serrated leaves.",
        "price": 80
    },
    {
        "id": 30,
        "name": "Rosemary",
        "image_url": "../assets/rosemary.jpg",
        "description": "A fragrant herb with needle-like leaves.",
        "price": 120
    },
    {
        "id": 31,
        "name": "Thyme",
        "image_url": "../assets/thyme.jpg",
        "description": "A low-growing herb with tiny, aromatic leaves.",
        "price": 90
    },
    {
        "id": 32,
        "name": "Lavender",
        "image_url": "../assets/lavender.jpg",
        "description": "A fragrant herb with purple spikes of flowers.",
        "price": 150
    },
    {
        "id": 33,
        "name": "Chamomile",
        "image_url": "../assets/chamomile.jpg",
        "description": "A herb with daisy-like flowers and a calming scent.",
        "price": 130
    },
    {
        "id": 34,
        "name": "Basil",
        "image_url": "../assets/basil.jpg",
        "description": "An herb with large, green leaves used in cooking.",
        "price": 100
    },
    {
        "id": 35,
        "name": "Cilantro",
        "image_url": "../assets/cilantro.jpg",
        "description": "A herb with delicate, lacy leaves used in cooking.",
        "price": 110
    },
    {
        "id": 36,
        "name": "Oregano",
        "image_url": "../assets/oregano.jpg",
        "description": "A herb with aromatic, oval leaves.",
        "price": 90
    },
    {
        "id": 37,
        "name": "Dill",
        "image_url": "../assets/dill.jpg",
        "description": "An herb with feathery leaves and a tangy flavor.",
        "price": 100
    },
    {
        "id": 38,
        "name": "Chives",
        "image_url": "../assets/chives.jpg",
        "description": "A herb with hollow, grass-like leaves used in cooking.",
        "price": 80
    },
    {
        "id": 39,
        "name": "Arugula",
        "image_url": "../assets/arugula.jpg",
        "description": "A leafy green with a peppery taste.",
        "price": 120
    },
    {
        "id": 40,
        "name": "Watercress",
        "image_url": "../assets/watercress.jpg",
        "description": "A water-loving herb with peppery leaves.",
        "price": 130
    },
    {
        "id": 41,
        "name": "Bay Leaf",
        "image_url": "../assets/bay_leaf.jpg",
        "description": "An herb with aromatic leaves used in cooking.",
        "price": 120
    },
    {
        "id": 42,
        "name": "Fennel",
        "image_url": "../assets/fennel.jpg",
        "description": "A herb with feathery leaves and a licorice-like flavor.",
        "price": 130
    },
    {
        "id": 43,
        "name": "Lovage",
        "image_url": "../assets/lovage.jpg",
        "description": "A herb with strong-flavored, celery-like leaves.",
        "price": 110
    },
    {
        "id": 44,
        "name": "Tarragon",
        "image_url": "../assets/tarragon.jpg",
        "description": "A herb with anise-like flavor and aromatic leaves.",
        "price": 120
    },
    {
        "id": 45,
        "name": "Lemon Thyme",
        "image_url": "../assets/lemon_thyme.jpg",
        "description": "A variety of thyme with a lemon scent.",
        "price": 130
    },
    {
        "id": 46,
        "name": "Wintergreen",
        "image_url": "../assets/wintergreen.jpg",
        "description": "A plant with evergreen leaves and a minty aroma.",
        "price": 140
    },
    {
        "id": 47,
        "name": "Chervil",
        "image_url": "../assets/chervil.jpg",
        "description": "A delicate herb with a mild anise flavor.",
        "price": 100
    },
    {
        "id": 48,
        "name": "Marjoram",
        "image_url": "../assets/marjoram.jpg",
        "description": "An herb with sweet, aromatic leaves used in cooking.",
        "price": 110
    },
    {
        "id": 49,
        "name": "Catnip",
        "image_url": "../assets/catnip.jpg",
        "description": "A herb known for its effect on cats, with aromatic leaves.",
        "price": 90
    }
]
